<?xml version="1.0" encoding="UTF-8"?>
<BUILDING>
    <LEVEL>
        <LABEL>0</LABEL>
        <HEIGHT>2.5</HEIGHT>
        <WIDTH>9</WIDTH>
        <LENGHT>8</LENGHT>
        <CAPACITY>120</CAPACITY>
        <ROOM>
            <LABEL>1</LABEL>
            <TYPE>NORMALROOM</TYPE>
            <HEIGHT>2.5</HEIGHT>
            <WIDTH>5</WIDTH>
            <LENGTH>5</LENGTH>
            <CAPACITY>40</CAPACITY>
            <SPRINKLER>YES</SPRINKLER>
            <SMOKEDETECTOR>YES</SMOKEDETECTOR>
            <EXTINGUISHERNUMBER>2</EXTINGUISHERNUMBER>
            <DOORNUMBER>1</DOORNUMBER>
            <DOOR>
                <ID>1</ID>
                <TYPE>EXTERNAL</TYPE>
                <CAPACITY>2</CAPACITY>
                <POSITION>NORTH</POSITION>
            </DOOR>
            <DOOR>
                <ID>2</ID>
                <TYPE>EXTERNAL</TYPE>
                <CAPACITY>1</CAPACITY>
                <POSITION>SOUTH</POSITION>
            </DOOR>
        </ROOM>
        <ROOM>
            <LABEL>2</LABEL>
            <TYPE>DELUXEROOM</TYPE>
            <HEIGHT>2.5</HEIGHT>
            <WIDTH>5</WIDTH>
            <LENGTH>5</LENGTH>
            <CAPACITY>80</CAPACITY>
            <SPRINKLER>YES</SPRINKLER>
            <SMOKEDETECTOR>YES</SMOKEDETECTOR>
            <EXTINGUISHERNUMBER>2</EXTINGUISHERNUMBER>
            <DOORNUMBER>1</DOORNUMBER>
            <DOOR>
                <ID>3</ID>
                <TYPE>EXTERNAL</TYPE>
                <CAPACITY>2</CAPACITY>
                <POSITION>NORTH</POSITION>
            </DOOR>
            <DOOR>
                <ID>4</ID>
                <TYPE>EXTERNAL</TYPE>
                <CAPACITY>1</CAPACITY>
                <POSITION>SOUTH</POSITION>
            </DOOR>
        </ROOM>
    </LEVEL>
</BUILDING>